cysox/__init__.py
cysox/__init__.pyi
cysox/__main__.py
cysox/audio.py
cysox/sox.cpython-312-x86_64-linux-gnu.so
cysox/sox.pyi
cysox/utils.py
cysox/utils.pyi
cysox/fx/__init__.py
cysox/fx/base.py
cysox/fx/convert.py
cysox/fx/eq.py
cysox/fx/filter.py
cysox/fx/reverb.py
cysox/fx/time.py
cysox/fx/volume.py
cysox.libs/libgomp-e985bcbb.so.1.0.0
cysox.libs/libgsm-6a620b60.so.1.0.17
cysox.libs/libltdl-e4b5b8dd.so.7
cysox.libs/libpng16-2bf8e833.so.16.34.0
cysox.libs/libsox-36efe91a.so.3.0.0
cysox-0.1.6.dist-info/METADATA
cysox-0.1.6.dist-info/WHEEL
cysox-0.1.6.dist-info/entry_points.txt
cysox-0.1.6.dist-info/RECORD
cysox-0.1.6.dist-info/licenses/LICENSE
cysox-0.1.6.dist-info/sboms/auditwheel.cdx.json
