Metadata-Version: 2.4
Name: cysox
Version: 0.1.6
Summary: A Pythonic audio processing library wrapping libsox
Keywords: audio,sound,sox,libsox,audio-processing,effects,cython,dsp
Author-Email: Shakeeb Alireza <shakfu@users.noreply.github.com>
Maintainer-Email: Shakeeb Alireza <shakfu@users.noreply.github.com>
License-Expression: MIT
Classifier: Development Status :: 4 - Beta
Classifier: Intended Audience :: Developers
Classifier: Intended Audience :: Science/Research
Classifier: Operating System :: MacOS
Classifier: Operating System :: POSIX :: Linux
Classifier: Programming Language :: Cython
Classifier: Programming Language :: Python :: 3
Classifier: Programming Language :: Python :: 3.9
Classifier: Programming Language :: Python :: 3.10
Classifier: Programming Language :: Python :: 3.11
Classifier: Programming Language :: Python :: 3.12
Classifier: Programming Language :: Python :: 3.13
Classifier: Programming Language :: Python :: 3.14
Classifier: Topic :: Multimedia :: Sound/Audio
Classifier: Topic :: Multimedia :: Sound/Audio :: Analysis
Classifier: Topic :: Multimedia :: Sound/Audio :: Conversion
Classifier: Topic :: Multimedia :: Sound/Audio :: Editors
Classifier: Topic :: Multimedia :: Sound/Audio :: Sound Synthesis
Classifier: Typing :: Typed
Project-URL: Homepage, https://github.com/shakfu/cysox
Project-URL: Repository, https://github.com/shakfu/cysox
Project-URL: Documentation, https://github.com/shakfu/cysox#readme
Project-URL: Issues, https://github.com/shakfu/cysox/issues
Project-URL: Changelog, https://github.com/shakfu/cysox/releases
Requires-Python: >=3.9
